simpel_utils/__init__.py
simpel_utils/apps.py
simpel_utils/avatars.py
simpel_utils/code.py
simpel_utils/contenttypes.py
simpel_utils/currency.py
simpel_utils/decorators.py
simpel_utils/loading.py
simpel_utils/settings.py
simpel_utils/slug.py
simpel_utils/templates.py
simpel_utils/tests.py
simpel_utils/urls.py
simpel_utils/validators.py
simpel_utils/version.py
simpel_utils/forms/__init__.py
simpel_utils/forms/fields.py
simpel_utils/locale/cs/LC_MESSAGES/django.mo
simpel_utils/locale/cs/LC_MESSAGES/django.po
simpel_utils/locale/de/LC_MESSAGES/django.mo
simpel_utils/locale/de/LC_MESSAGES/django.po
simpel_utils/locale/fa/LC_MESSAGES/django.mo
simpel_utils/locale/fa/LC_MESSAGES/django.po
simpel_utils/locale/ru/LC_MESSAGES/django.mo
simpel_utils/locale/ru/LC_MESSAGES/django.po
simpel_utils/locale/zh_Hans/LC_MESSAGES/django.mo
simpel_utils/locale/zh_Hans/LC_MESSAGES/django.po
simpel_utils/models/__init__.py
simpel_utils/models/actions.py
simpel_utils/models/choices.py
simpel_utils/models/fields.py
simpel_utils/models/managers.py
simpel_utils/models/models.py
simpel_utils/models/paranoid.py
simpel_utils/models/signals.py
simpel_utils/models/tracker.py
simpel_utils-0.1.2.dist-info/LICENSE
simpel_utils-0.1.2.dist-info/METADATA
simpel_utils-0.1.2.dist-info/WHEEL
simpel_utils-0.1.2.dist-info/top_level.txt
simpel_utils-0.1.2.dist-info/RECORD
